<?xml version="1.0" encoding="UTF-8"?>
<term>
  <id>00745</id>
  <doi>10.1351/goldbook.B00745</doi>
  <code>B00745</code>
  <status>current</status>
  <longtitle>IUPAC Gold Book - Brønsted base</longtitle>
  <title>Brønsted base</title>
  <termversion>2.3.3</termversion>
  <lastupdated>2014-02-24</lastupdated>
  <definitions>
    <item>
      <id>1</id>
      <text>A molecular entity capable of accepting a hydron (proton) from an acid (i.e. a 'hydron acceptor') or the corresponding chemical species. For example: OH−, H2O, CH3CO2−, HSO4−, SO42−, Cl−.</text>
      <links>
        <item>
          <title>conjugate acid–base pair</title>
          <url>https://goldbook.iupac.org/terms/view/C01266</url>
        </item>
        <item>
          <title>conjugate acid–base pair</title>
          <url>https://goldbook.iupac.org/terms/view/C01266</url>
        </item>
        <item>
          <title>molecular entity</title>
          <url>https://goldbook.iupac.org/terms/view/M03986</url>
        </item>
        <item>
          <title>hydron</title>
          <url>https://goldbook.iupac.org/terms/view/H02904</url>
        </item>
        <item>
          <title>chemical species</title>
          <url>https://goldbook.iupac.org/terms/view/CT01038</url>
        </item>
        <item>
          <title>conjugate acid–base pair</title>
          <url>https://goldbook.iupac.org/terms/view/C01266</url>
        </item>
        <item>
          <title>molecular entity</title>
          <url>https://goldbook.iupac.org/terms/view/M03986</url>
        </item>
        <item>
          <title>hydron</title>
          <url>https://goldbook.iupac.org/terms/view/H02904</url>
        </item>
        <item>
          <title>chemical species</title>
          <url>https://goldbook.iupac.org/terms/view/CT01038</url>
        </item>
        <item>
          <title>proton</title>
          <url>https://goldbook.iupac.org/terms/view/P04906</url>
        </item>
      </links>
      <sources>
        <item>PAC, 1994, 66, 1077. 'Glossary of terms used in physical organic chemistry (IUPAC Recommendations 1994)' on page 1091 (https://doi.org/10.1351/pac199466051077)</item>
      </sources>
    </item>
  </definitions>
  <referencedin>
    <item>
      <title>Wikipedia - Emäs (fi)</title>
      <url>https://fi.wikipedia.org/wiki/Emäs</url>
    </item>
    <item>
      <title>Wikipedia - Happo-emäsreaktio (fi)</title>
      <url>https://fi.wikipedia.org/wiki/Happo-emäsreaktio</url>
    </item>
    <item>
      <title>Wikipedia - Нигез (химия) (tt)</title>
      <url>https://tt.wikipedia.org/wiki/Нигез_(химия)</url>
    </item>
    <item>
      <title>Wikipedia - Основа (химия) (bg)</title>
      <url>https://bg.wikipedia.org/wiki/Основа_(химия)</url>
    </item>
    <item>
      <title>Wikipedia - Основание (химия) (ru)</title>
      <url>https://ru.wikipedia.org/wiki/Основание_(химия)</url>
    </item>
    <item>
      <title>Wikipedia - 塩基 (ja)</title>
      <url>https://ja.wikipedia.org/wiki/塩基</url>
    </item>
  </referencedin>
  <links>
    <html>https://goldbook.iupac.org/terms/view/B00745/html</html>
    <json>https://goldbook.iupac.org/terms/view/B00745/json</json>
    <xml>https://goldbook.iupac.org/terms/view/B00745/xml</xml>
    <plain>https://goldbook.iupac.org/terms/view/B00745/plain</plain>
  </links>
  <citation>Citation: 'Brønsted base' in IUPAC Compendium of Chemical Terminology, 5th ed. International Union of Pure and Applied Chemistry; 2025. Online version 5.0.0, 2025. 10.1351/goldbook.B00745</citation>
  <license>The IUPAC Gold Book is licensed under Creative Commons Attribution-ShareAlike CC BY-SA 4.0 International (https://creativecommons.org/licenses/by-sa/4.0/) for individual terms.</license>
  <collection>If you are interested in licensing the Gold Book for commercial use, please contact the IUPAC Executive Director at executivedirector@iupac.org .</collection>
  <disclaimer>The International Union of Pure and Applied Chemistry (IUPAC) is continuously reviewing and, where needed, updating terms in the Compendium of Chemical Terminology (the IUPAC Gold Book). Users of these terms are encouraged to include the version of a term with its use and to check regularly for updates to term definitions that you are using.</disclaimer>
  <accessed>2025-02-25T07:16:39+00:00</accessed>
</term>
