<?xml version="1.0" encoding="UTF-8"?>
<term>
  <id>01573</id>
  <doi>10.1351/goldbook.D01573</doi>
  <code>D01573</code>
  <status>current</status>
  <longtitle>IUPAC Gold Book - degrees of triad isotacticity, syndiotacticity, and heterotacticity</longtitle>
  <title>degrees of triad isotacticity, syndiotacticity, and heterotacticity</title>
  <termversion>2.3.3</termversion>
  <lastupdated>2014-02-24</lastupdated>
  <definitions>
    <item>
      <id>1</id>
      <text>The fractions of triads in a regular vinyl polymer that are of the mm, rr and mr = rm types, respectively. In cases where triad analysis is not attainable, the diad isotacticity and diad syndiotacticity may be defined as the fractions of diads in a regular vinyl polymer that are of the m and r types, respectively. (m = meso; r = racemic).</text>
      <links>
        <item>
          <title>triads (in polymers)</title>
          <url>https://goldbook.iupac.org/terms/view/C01287</url>
        </item>
        <item>
          <title>polymer (in polymers)</title>
          <url>https://goldbook.iupac.org/terms/view/P04735</url>
        </item>
        <item>
          <title>triads (in polymers)</title>
          <url>https://goldbook.iupac.org/terms/view/C01287</url>
        </item>
        <item>
          <title>polymer (in polymers)</title>
          <url>https://goldbook.iupac.org/terms/view/P04735</url>
        </item>
        <item>
          <title>meso (in polymers)</title>
          <url>https://goldbook.iupac.org/terms/view/M03838</url>
        </item>
        <item>
          <title>racemic (in polymers)</title>
          <url>https://goldbook.iupac.org/terms/view/R05026</url>
        </item>
      </links>
      <sources>
        <item>Purple Book, 1st ed., p. 45 (http://old.iupac.org/publications/books/author/metanomski.html)</item>
      </sources>
    </item>
  </definitions>
  <links>
    <html>https://goldbook.iupac.org/terms/view/D01573/html</html>
    <json>https://goldbook.iupac.org/terms/view/D01573/json</json>
    <xml>https://goldbook.iupac.org/terms/view/D01573/xml</xml>
    <plain>https://goldbook.iupac.org/terms/view/D01573/plain</plain>
  </links>
  <citation>Citation: 'degrees of triad isotacticity, syndiotacticity, and heterotacticity' in IUPAC Compendium of Chemical Terminology, 5th ed. International Union of Pure and Applied Chemistry; 2025. Online version 5.0.0, 2025. 10.1351/goldbook.D01573</citation>
  <license>The IUPAC Gold Book is licensed under Creative Commons Attribution-ShareAlike CC BY-SA 4.0 International (https://creativecommons.org/licenses/by-sa/4.0/) for individual terms.</license>
  <collection>If you are interested in licensing the Gold Book for commercial use, please contact the IUPAC Executive Director at executivedirector@iupac.org .</collection>
  <disclaimer>The International Union of Pure and Applied Chemistry (IUPAC) is continuously reviewing and, where needed, updating terms in the Compendium of Chemical Terminology (the IUPAC Gold Book). Users of these terms are encouraged to include the version of a term with its use and to check regularly for updates to term definitions that you are using.</disclaimer>
  <accessed>2025-02-25T07:55:02+00:00</accessed>
</term>
