<?xml version="1.0" encoding="UTF-8"?>
<term>
  <id>02243</id>
  <doi>10.1351/goldbook.E02243</doi>
  <code>E02243</code>
  <status>current</status>
  <longtitle>IUPAC Gold Book - excimer laser</longtitle>
  <title>excimer laser</title>
  <abbrevs>
    <item>UV</item>
  </abbrevs>
  <termversion>2.3.3</termversion>
  <lastupdated>2014-02-24</lastupdated>
  <definitions>
    <item>
      <id>1</id>
      <text>A source of pulsed coherent radiation obtained from an exciplex. The proper name is exciplexlaser. Typical lasing species are noble gas halides (XeCl, KrF, etc.) emitting in the UV domain.</text>
      <links>
        <item>
          <title>coherent radiation</title>
          <url>https://goldbook.iupac.org/terms/view/C01130</url>
        </item>
        <item>
          <title>exciplex</title>
          <url>https://goldbook.iupac.org/terms/view/E02246</url>
        </item>
        <item>
          <title>laser</title>
          <url>https://goldbook.iupac.org/terms/view/L03459</url>
        </item>
        <item>
          <title>lasing</title>
          <url>https://goldbook.iupac.org/terms/view/L03479</url>
        </item>
        <item>
          <title>coherent radiation</title>
          <url>https://goldbook.iupac.org/terms/view/C01130</url>
        </item>
        <item>
          <title>exciplex</title>
          <url>https://goldbook.iupac.org/terms/view/E02246</url>
        </item>
        <item>
          <title>laser</title>
          <url>https://goldbook.iupac.org/terms/view/L03459</url>
        </item>
        <item>
          <title>lasing</title>
          <url>https://goldbook.iupac.org/terms/view/L03479</url>
        </item>
        <item>
          <title>gas lasers</title>
          <url>https://goldbook.iupac.org/terms/view/G02585</url>
        </item>
      </links>
      <sources>
        <item>PAC, 1995, 67, 1913. 'Nomenclature, symbols, units, and their usage in spectrochemical analysis-XV. Laser-based molecular spectroscopy for chemical analysis - laser fundamentals (IUPAC Recommendations 1995)' on page 1920 (https://doi.org/10.1351/pac199567111913)</item>
        <item>PAC, 1996, 68, 2223. 'Glossary of terms used in photochemistry (IUPAC Recommendations 1996)' on page 2241 (https://doi.org/10.1351/pac199668122223)</item>
      </sources>
    </item>
  </definitions>
  <referencedin>
    <item>
      <title>Wikipedia - Excimer laser (en)</title>
      <url>https://en.wikipedia.org/wiki/Excimer_laser</url>
    </item>
    <item>
      <title>Wikipedia - Excimerový laser (sk)</title>
      <url>https://sk.wikipedia.org/wiki/Excimerový_laser</url>
    </item>
    <item>
      <title>Wikipedia - Laser a eccimeri (it)</title>
      <url>https://it.wikipedia.org/wiki/Laser_a_eccimeri</url>
    </item>
    <item>
      <title>Wikipedia - Laser à excimère (fr)</title>
      <url>https://fr.wikipedia.org/wiki/Laser_à_excimère</url>
    </item>
    <item>
      <title>Wikipedia - ليزر إكسيمر (ar)</title>
      <url>https://ar.wikipedia.org/wiki/ليزر_إكسيمر</url>
    </item>
    <item>
      <title>Wikipedia - لیزر برانگیخته‌پار (fa)</title>
      <url>https://fa.wikipedia.org/wiki/لیزر_برانگیخته‌پار</url>
    </item>
  </referencedin>
  <links>
    <html>https://goldbook.iupac.org/terms/view/E02243/html</html>
    <json>https://goldbook.iupac.org/terms/view/E02243/json</json>
    <xml>https://goldbook.iupac.org/terms/view/E02243/xml</xml>
    <plain>https://goldbook.iupac.org/terms/view/E02243/plain</plain>
  </links>
  <citation>Citation: 'excimer laser' in IUPAC Compendium of Chemical Terminology, 5th ed. International Union of Pure and Applied Chemistry; 2025. Online version 5.0.0, 2025. 10.1351/goldbook.E02243</citation>
  <license>The IUPAC Gold Book is licensed under Creative Commons Attribution-ShareAlike CC BY-SA 4.0 International (https://creativecommons.org/licenses/by-sa/4.0/) for individual terms.</license>
  <collection>If you are interested in licensing the Gold Book for commercial use, please contact the IUPAC Executive Director at executivedirector@iupac.org .</collection>
  <disclaimer>The International Union of Pure and Applied Chemistry (IUPAC) is continuously reviewing and, where needed, updating terms in the Compendium of Chemical Terminology (the IUPAC Gold Book). Users of these terms are encouraged to include the version of a term with its use and to check regularly for updates to term definitions that you are using.</disclaimer>
  <accessed>2025-02-25T08:24:46+00:00</accessed>
</term>
