<?xml version="1.0" encoding="UTF-8"?>
<term>
  <id>07264</id>
  <doi>10.1351/goldbook.PT07264</doi>
  <code>PT07264</code>
  <status>current</status>
  <longtitle>IUPAC Gold Book - polymer alloy</longtitle>
  <title>polymer alloy</title>
  <termversion>2.3.3</termversion>
  <lastupdated>2014-02-24</lastupdated>
  <definitions>
    <item>
      <id>1</id>
      <text>Polymeric material, exhibiting macroscopically uniform physical properties throughout its whole volume, that comprises a compatible polymer blend, a miscible polymer blend or a multiphase copolymer.</text>
      <links>
        <item>
          <title>Polymeric</title>
          <url>https://goldbook.iupac.org/terms/view/M03667</url>
        </item>
        <item>
          <title>compatible polymer blend</title>
          <url>https://goldbook.iupac.org/terms/view/CT07581</url>
        </item>
        <item>
          <title>miscible polymer blend</title>
          <url>https://goldbook.iupac.org/terms/view/HT07582</url>
        </item>
        <item>
          <title>multiphase copolymer</title>
          <url>https://goldbook.iupac.org/terms/view/MT07287</url>
        </item>
      </links>
      <sources>
        <item>PAC, 2007, 79, 1801. 'Definitions of terms relating to the structure and processing of sols, gels, networks, and inorganic-organic hybrid materials (IUPAC Recommendations 2007)' on page 1816 (https://doi.org/10.1351/pac200779101801)</item>
      </sources>
    </item>
  </definitions>
  <links>
    <html>https://goldbook.iupac.org/terms/view/PT07264/html</html>
    <json>https://goldbook.iupac.org/terms/view/PT07264/json</json>
    <xml>https://goldbook.iupac.org/terms/view/PT07264/xml</xml>
    <plain>https://goldbook.iupac.org/terms/view/PT07264/plain</plain>
  </links>
  <citation>Citation: 'polymer alloy' in IUPAC Compendium of Chemical Terminology, 5th ed. International Union of Pure and Applied Chemistry; 2025. Online version 5.0.0, 2025. 10.1351/goldbook.PT07264</citation>
  <license>The IUPAC Gold Book is licensed under Creative Commons Attribution-ShareAlike CC BY-SA 4.0 International (https://creativecommons.org/licenses/by-sa/4.0/) for individual terms.</license>
  <collection>If you are interested in licensing the Gold Book for commercial use, please contact the IUPAC Executive Director at executivedirector@iupac.org .</collection>
  <disclaimer>The International Union of Pure and Applied Chemistry (IUPAC) is continuously reviewing and, where needed, updating terms in the Compendium of Chemical Terminology (the IUPAC Gold Book). Users of these terms are encouraged to include the version of a term with its use and to check regularly for updates to term definitions that you are using.</disclaimer>
  <accessed>2025-02-25T10:27:03+00:00</accessed>
</term>
